setup.py
MesonPy/AESCipher.py
MesonPy/BackendApplication.py
MesonPy/Constants.py
MesonPy/FrontalController.py
MesonPy/FrontendApplication.py
MesonPy/__init__.py
MesonPy.egg-info/PKG-INFO
MesonPy.egg-info/SOURCES.txt
MesonPy.egg-info/dependency_links.txt
MesonPy.egg-info/requires.txt
MesonPy.egg-info/top_level.txt
MesonPy/Communication/Duplex.py
MesonPy/Communication/Pipeline.py
MesonPy/Communication/Session.py
MesonPy/Communication/__init__.py
MesonPy/Communication/DistributedObject/DistributedObjectMapper.py
MesonPy/Communication/DistributedObject/SkeletonManager.py
MesonPy/Communication/DistributedObject/StubManager.py
MesonPy/Communication/DistributedObject/__init__.py
MesonPy/Communication/IncomingHandler/BaseMessageReceiver.py
MesonPy/Communication/IncomingHandler/FormatRouter.py
MesonPy/Communication/IncomingHandler/ObjectUnmarshaller.py
MesonPy/Communication/IncomingHandler/OperationRouter.py
MesonPy/Communication/IncomingHandler/RootIncomingHandler.py
MesonPy/Communication/IncomingHandler/SecurityHandler.py
MesonPy/Communication/IncomingHandler/__init__.py
MesonPy/Communication/OutcomingHandler/BaseMessageSender.py
MesonPy/Communication/OutcomingHandler/FormatRouter.py
MesonPy/Communication/OutcomingHandler/OperationRouter.py
MesonPy/Communication/OutcomingHandler/RootOutcomingHandler.py
MesonPy/Communication/OutcomingHandler/SecurityHandler.py
MesonPy/Communication/OutcomingHandler/__init__.py
MesonPy/Processor/Kernel.py
MesonPy/Processor/Processor.py
MesonPy/Processor/PubSub.py
MesonPy/Processor/RPC.py
MesonPy/Processor/__init__.py
MesonPy/Service/ServiceInjector.py
MesonPy/Service/__init__.py