Metadata-Version: 1.0
Name: MesonPy
Version: 0.0.1
Summary: Websocket based python wrapper for Electron projects
Home-page: https://github.com/Bartpab/meson-py
Author: Gael Pabois
Author-email: gael.pabois@gmail.com
License: LICENSE
Platform: UNKNOWN
